ezpyqt/__init__.py
ezpyqt/constants.py
ezpyqt/ezpyqt.py
ezpyqt-1.0.3.dist-info/METADATA
ezpyqt-1.0.3.dist-info/WHEEL
ezpyqt-1.0.3.dist-info/top_level.txt
ezpyqt-1.0.3.dist-info/RECORD
