Metadata-Version: 2.1
Name: ezpyqt
Version: 1.0.3
Summary: To make the use of PyQt easier, Hence the name ezpyqt!
Home-page: https://github.com/saeidalz13/ezpyqt
Author: Saeid Alizadeh
Author-email: saeidalz96@gmail.com
Requires-Dist: PySide6
